{"goal":
  {
    "preferences":[[1.0,2.0],[3.0,1.0]],
    "children":[{"preferences":[[1.0,5.0],[5.0,1.0]],
      "children":
      [
        {
          "preferences":[[1.0,2.0,3.0],[1.0,1.0,2.0],[3.0,4.0,1.0]],
          "children":[],
          "name":"bilety"},
        {
          "preferences":[[1.0,1.0,2.0],[3.0,1.0,1.0],[2.0,4.0,1.0]],
          "children":[],"name":"hotel"}],
      "name":"koszt"}
    , {
        "preferences":[[1.0,3.2,3.0],[1.0,1.0,2.0],[4.0,5.0,1.0]],
        "children":[],
        "name":"atrakcje"}
    ],
    "name":"Wakacje"
  },
  "alternatives":["Paryż","Mediolan","Barcelona"]}